test/snapshots/__init__.py
test/snapshots/snap_gulp_pdf_test.py
toggle_report_to_gulp/__init__.py
toggle_report_to_gulp/gulp_pdf.py
toggle_report_to_gulp/report.py
toggle_report_to_gulp/report_summary.py
toggle_report_to_gulp/toggl_client.py
toggle_report_to_gulp/utils.py
toggl_report-1.0.7.dist-info/LICENSE
toggl_report-1.0.7.dist-info/METADATA
toggl_report-1.0.7.dist-info/WHEEL
toggl_report-1.0.7.dist-info/entry_points.txt
toggl_report-1.0.7.dist-info/top_level.txt
toggl_report-1.0.7.dist-info/RECORD
