Metadata-Version: 2.1
Name: toggl-report
Version: 1.0.7
Summary: Generate PDF report from toggl
Home-page: https://github.com/alexzelenuyk/toggl-report-to-gulp
Author: Oleksii Zeleniuk
License: MIT
Platform: UNKNOWN
Classifier: License :: OSI Approved :: MIT License
Classifier: Programming Language :: Python :: 3
Classifier: Programming Language :: Python :: 3.8
Requires-Dist: fpdf
Requires-Dist: iso8601
Requires-Dist: requests
